pyrepltalk-1.1.1.dist-info/DESCRIPTION.rst
pyrepltalk-1.1.1.dist-info/METADATA
pyrepltalk-1.1.1.dist-info/RECORD
pyrepltalk-1.1.1.dist-info/WHEEL
pyrepltalk-1.1.1.dist-info/entry_points.txt
pyrepltalk-1.1.1.dist-info/metadata.json
pyrepltalk-1.1.1.dist-info/top_level.txt
repltalk/__init__.py
repltalk/baseadapter.py
repltalk/baserepl.py
repltalk/baserunner.py
repltalk/adapters/__init__.py
repltalk/adapters/nvim.py
repltalk/adapters/vim.py
repltalk/servers/__init__.py
repltalk/servers/elm.py
repltalk/servers/elm18.py
repltalk/servers/haskell.py
