Metadata-Version: 2.0
Name: pyrepltalk
Version: 1.1.1
Summary: Talk to REPLs from code editors
Home-page: http://github.com/sras/repltalk
Author: Sandeep.C.R
Author-email: sandeep@sras.me
License: MIT
Platform: UNKNOWN
Requires-Dist: pexpect
Requires-Dist: bottle
